setup.py
distributions_Olabisi/Binomialdistribution.py
distributions_Olabisi/Gaussiandistribution.py
distributions_Olabisi/Generaldistribution.py
distributions_Olabisi/__init__.py
distributions_Olabisi.egg-info/PKG-INFO
distributions_Olabisi.egg-info/SOURCES.txt
distributions_Olabisi.egg-info/dependency_links.txt
distributions_Olabisi.egg-info/not-zip-safe
distributions_Olabisi.egg-info/top_level.txt