Metadata-Version: 1.0
Name: distributions-Olabisi
Version: 0.3
Summary: Gaussian and Binomial distributions
Home-page: UNKNOWN
Author: olabisi
Author-email: UNKNOWN
License: UNKNOWN
Platform: UNKNOWN
